{
    "id": 119,
    "name": "足音ループ",
    "description": "",
    "commands": [
        {
            "code": 111,
            "codeStr": "VariableCondition",
            "intArgs": [
                2,
                1600000,
                1,
                2,
                1600000,
                4294967295,
                2
            ],
            "index": 0
        },
        {
            "code": 401,
            "codeStr": "ChoiceCase",
            "intArgs": [
                1
            ],
            "index": 1
        },
        {
            "code": 121,
            "codeStr": "SetVariable",
            "intArgs": [
                1600000,
                0,
                0,
                0
            ],
            "index": 2
        },
        {
            "code": 121,
            "codeStr": "SetVariable",
            "intArgs": [
                1600022,
                100,
                0,
                0
            ],
            "index": 3
        },
        {
            "code": 121,
            "codeStr": "SetVariable",
            "intArgs": [
                1600023,
                0,
                0,
                0
            ],
            "index": 4
        },
        {
            "code": 121,
            "codeStr": "SetVariable",
            "intArgs": [
                1600099,
                1,
                0,
                0
            ],
            "index": 5
        },
        {
            "code": 401,
            "codeStr": "ChoiceCase",
            "intArgs": [
                2
            ],
            "index": 8
        },
        {
            "code": 121,
            "codeStr": "SetVariable",
            "intArgs": [
                1600000,
                0,
                0,
                0
            ],
            "index": 9
        },
        {
            "code": 121,
            "codeStr": "SetVariable",
            "intArgs": [
                1600099,
                0,
                0,
                0
            ],
            "index": 10
        },
        {
            "code": 250,
            "codeStr": "Database",
            "stringArgs": [
                "",
                "",
                "",
                ""
            ],
            "intArgs": [
                0,
                1600001,
                0,
                4608,
                1600005
            ],
            "index": 14
        },
        {
            "code": 111,
            "codeStr": "VariableCondition",
            "intArgs": [
                2,
                1600023,
                0,
                2,
                1600023,
                1,
                2
            ],
            "index": 15
        },
        {
            "code": 401,
            "codeStr": "ChoiceCase",
            "intArgs": [
                1
            ],
            "index": 16
        },
        {
            "code": 121,
            "codeStr": "SetVariable",
            "intArgs": [
                1600022,
                100,
                0,
                0
            ],
            "index": 17
        },
        {
            "code": 121,
            "codeStr": "SetVariable",
            "intArgs": [
                1600023,
                1,
                0,
                0
            ],
            "index": 18
        },
        {
            "code": 401,
            "codeStr": "ChoiceCase",
            "intArgs": [
                2
            ],
            "index": 20
        },
        {
            "code": 121,
            "codeStr": "SetVariable",
            "intArgs": [
                1600022,
                80,
                0,
                24576
            ],
            "index": 21
        },
        {
            "code": 121,
            "codeStr": "SetVariable",
            "intArgs": [
                1600023,
                0,
                0,
                0
            ],
            "index": 22
        },
        {
            "code": 121,
            "codeStr": "SetVariable",
            "intArgs": [
                1600022,
                80,
                100,
                24576
            ],
            "index": 25
        },
        {
            "code": 140,
            "codeStr": "Sound",
            "stringArgs": [
                "\\cself[5]"
            ],
            "intArgs": [
                33554464,
                0,
                0,
                0,
                100,
                1600022,
                0
            ],
            "index": 26
        },
        {
            "code": 180,
            "codeStr": "Wait",
            "intArgs": [
                1600002
            ],
            "index": 27
        }
    ]
}