{
    "id": 127,
    "name": "メモを読む",
    "description": "",
    "commands": [
        {
            "code": 121,
            "codeStr": "SetVariable",
            "intArgs": [
                1600010,
                91000,
                0,
                0
            ],
            "index": 0
        },
        {
            "code": 121,
            "codeStr": "SetVariable",
            "intArgs": [
                1600013,
                1600010,
                0,
                0
            ],
            "index": 1
        },
        {
            "code": 121,
            "codeStr": "SetVariable",
            "intArgs": [
                1600011,
                320,
                0,
                0
            ],
            "index": 2
        },
        {
            "code": 121,
            "codeStr": "SetVariable",
            "intArgs": [
                1600012,
                180,
                0,
                0
            ],
            "index": 3
        },
        {
            "code": 140,
            "codeStr": "Sound",
            "stringArgs": [
                "SE/onjin_shinbun_toru.ogg"
            ],
            "intArgs": [
                33554464,
                0,
                0,
                0,
                100,
                100
            ],
            "index": 4
        },
        {
            "code": 150,
            "codeStr": "Picture",
            "stringArgs": [
                "Picture/win_memo.png"
            ],
            "intArgs": [
                4096,
                1600010,
                0,
                1,
                1,
                1,
                255,
                1600011,
                1600012,
                50,
                0
            ],
            "index": 5
        },
        {
            "code": 121,
            "codeStr": "SetVariable",
            "intArgs": [
                1600011,
                320,
                0,
                0
            ],
            "index": 6
        },
        {
            "code": 121,
            "codeStr": "SetVariable",
            "intArgs": [
                1600012,
                180,
                0,
                0
            ],
            "index": 7
        },
        {
            "code": 121,
            "codeStr": "SetVariable",
            "intArgs": [
                1600010,
                1,
                0,
                256
            ],
            "index": 8
        },
        {
            "code": 150,
            "codeStr": "Picture",
            "stringArgs": [
                "\\s[10]"
            ],
            "intArgs": [
                4128,
                1600010,
                0,
                1,
                1,
                1,
                255,
                1600011,
                1600012,
                100,
                0,
                0,
                33554432,
                0,
                0,
                0,
                0,
                0
            ],
            "index": 9
        },
        {
            "code": 180,
            "codeStr": "Wait",
            "intArgs": [
                20
            ],
            "index": 10
        },
        {
            "code": 123,
            "codeStr": "InputKey",
            "intArgs": [
                1600020,
                177
            ],
            "index": 11
        },
        {
            "code": 150,
            "codeStr": "Picture",
            "intArgs": [
                16777218,
                1600013,
                0,
                0,
                0,
                1600010
            ],
            "index": 12
        },
        {
            "code": 180,
            "codeStr": "Wait",
            "intArgs": [
                20
            ],
            "index": 13
        }
    ]
}